IPS_Common_Library-0.1.20.data/data/ips_common/config/config.yaml
ips_common/__init__.py
ips_common/ips_logging.py
ips_common/config/__init__.py
ips_common/config/config.yaml
ips_common/config/configuration.py
IPS_Common_Library-0.1.20.dist-info/AUTHORS
IPS_Common_Library-0.1.20.dist-info/LICENSE
IPS_Common_Library-0.1.20.dist-info/METADATA
IPS_Common_Library-0.1.20.dist-info/WHEEL
IPS_Common_Library-0.1.20.dist-info/pbr.json
IPS_Common_Library-0.1.20.dist-info/top_level.txt
IPS_Common_Library-0.1.20.dist-info/RECORD
